page2img.py
ocrd_format_converters-0.1.0.dist-info/licenses/LICENSE
ocrd_format_converters-0.1.0.dist-info/METADATA
ocrd_format_converters-0.1.0.dist-info/WHEEL
ocrd_format_converters-0.1.0.dist-info/entry_points.txt
ocrd_format_converters-0.1.0.dist-info/top_level.txt
ocrd_format_converters-0.1.0.dist-info/RECORD
