Metadata-Version: 2.4
Name: ocrd-format-converters
Version: 0.1.0
Summary: Converters for various file formats used for representing OCR
Author-email: Frank Wiegand <frank.wiegand@gmail.com>, Matthias Boenig <matthiasboenig@gmx.net>, Marius Hug <marius.hug@googlemail.com>, Kay-Michael Wuerzner <wuerzner@gmail.com>
License:                                  Apache License
Project-URL: Homepage, https://github.com/OCR-D/format-converters
Project-URL: Repository, https://github.com/OCR-D/format-converters.git
Requires-Python: >=3.8
License-File: LICENSE
Requires-Dist: click
Requires-Dist: lxml
Requires-Dist: validators
Requires-Dist: Pillow
Dynamic: license-file
